fetch-latest-file/__init__.py
fetch-latest-file/config.py
fetch-latest-file/default_command.py
fetch-latest-file/fetch_latest_file.py
fetch_latest_file/__init__.py
fetch_latest_file/config.py
fetch_latest_file/default_command.py
fetch_latest_file/fetch_latest_file.py
fetch_latest_file1-0.1.8.dist-info/LICENSE
fetch_latest_file1-0.1.8.dist-info/METADATA
fetch_latest_file1-0.1.8.dist-info/WHEEL
fetch_latest_file1-0.1.8.dist-info/entry_points.txt
fetch_latest_file1-0.1.8.dist-info/top_level.txt
fetch_latest_file1-0.1.8.dist-info/RECORD
