Metadata-Version: 2.1
Name: fetch-latest-file1
Version: 0.1.8
Summary: Easy fetch a latest file.
Home-page: https://github.com/marcwimmer/fetch-latest-file
Author: Marc-Christian Wimmer
Author-email: marc@itewimmer.de
License: MIT
Platform: UNKNOWN
Requires-Python: >=3.6.0
License-File: LICENSE
Requires-Dist: click
Requires-Dist: inquirer
Requires-Dist: arrow
Requires-Dist: pathlib
Requires-Dist: click-completion-helper
Requires-Dist: click-default-group
